ppdes/__init__.py
ppdes/base.py
ppdes/data.py
ppdes/diffsolve.py
ppdes/err.py
ppdes/fztest.py
ppdes/ode_main.py
ppdes/pde_solver.py
ppdes/solver.py
ppdes-0.1.0.dist-info/METADATA
ppdes-0.1.0.dist-info/WHEEL
ppdes-0.1.0.dist-info/top_level.txt
ppdes-0.1.0.dist-info/RECORD
