Metadata-Version: 2.1
Name: ppdes
Version: 0.1.0
Summary: a ped solver
Home-page: UNKNOWN
License: MIT Licence
Keywords: math
Platform: all
Classifier: Programming Language :: Python
Classifier: Programming Language :: Python :: 3
Requires-Python: >=3
